odoo/addons/purchase_requisition_tier_validation/README.rst
odoo/addons/purchase_requisition_tier_validation/__init__.py
odoo/addons/purchase_requisition_tier_validation/__manifest__.py
odoo/addons/purchase_requisition_tier_validation/i18n/es.po
odoo/addons/purchase_requisition_tier_validation/i18n/it.po
odoo/addons/purchase_requisition_tier_validation/i18n/purchase_requisition_tier_validation.pot
odoo/addons/purchase_requisition_tier_validation/i18n/zh_CN.po
odoo/addons/purchase_requisition_tier_validation/models/__init__.py
odoo/addons/purchase_requisition_tier_validation/models/purchase_requisition.py
odoo/addons/purchase_requisition_tier_validation/models/tier_definition.py
odoo/addons/purchase_requisition_tier_validation/readme/CONFIGURE.md
odoo/addons/purchase_requisition_tier_validation/readme/CONTRIBUTORS.md
odoo/addons/purchase_requisition_tier_validation/readme/CREDITS.md
odoo/addons/purchase_requisition_tier_validation/readme/DESCRIPTION.md
odoo/addons/purchase_requisition_tier_validation/readme/INSTALL.md
odoo/addons/purchase_requisition_tier_validation/readme/USAGE.md
odoo/addons/purchase_requisition_tier_validation/static/description/icon.png
odoo/addons/purchase_requisition_tier_validation/static/description/index.html
odoo/addons/purchase_requisition_tier_validation/tests/__init__.py
odoo/addons/purchase_requisition_tier_validation/tests/test_purchase_requisition_tier_validation.py
odoo/addons/purchase_requisition_tier_validation/views/purchase_requisition_view.xml
odoo_addon_purchase_requisition_tier_validation-17.0.1.0.0.10.dist-info/METADATA
odoo_addon_purchase_requisition_tier_validation-17.0.1.0.0.10.dist-info/WHEEL
odoo_addon_purchase_requisition_tier_validation-17.0.1.0.0.10.dist-info/top_level.txt
odoo_addon_purchase_requisition_tier_validation-17.0.1.0.0.10.dist-info/RECORD
