Metadata-Version: 2.1
Name: odoo-addon-purchase_requisition_tier_validation
Version: 17.0.1.0.0.10
Requires-Python: >=3.10
Requires-Dist: odoo-addon-base_tier_validation>=17.0dev,<17.1dev
Requires-Dist: odoo>=17.0a,<17.1dev
Summary: Extends the functionality of Purchase Agreements to support a tier validation process.
Home-page: https://github.com/OCA/purchase-workflow
License: AGPL-3
Author: Ecosoft, Odoo Community Association (OCA)
Author-email: support@odoo-community.org
Classifier: Programming Language :: Python
Classifier: Framework :: Odoo
Classifier: Framework :: Odoo :: 17.0
Classifier: License :: OSI Approved :: GNU Affero General Public License v3
